{
  "en": {
    "app.title": "EasySave",
    "menu.file": "File",
    "menu.file.download": "Download Backup",
    "menu.file.save": "Save Project",
    "menu.file.exit": "Exit",
    "menu.settings": "Settings",
    "menu.settings.autosave": "Toggle Auto-Save",
    "menu.settings.config": "Modify Config",
    "menu.view": "View",
    "menu.view.logs": "Show Logs",
    "backup.title": "Backup Operations",
    "backup.name": "Name",
    "backup.source": "Source",
    "backup.destination": "Destination",
    "backup.type": "Type",
    "backup.status": "Status",
    "backup.progress": "Progress",
    "config.title": "Configuration",
    "config.language": "Language",
    "config.logpath": "Log File Path",
    "config.statuspath": "Status File Path",
    "config.autosave": "Auto-Save",
    "config.save": "Save",
    "config.cancel": "Cancel",
    "logs.title": "Application Logs",
    "logs.timestamp": "Timestamp",
    "logs.level": "Level",
    "logs.message": "Message",
    "logs.refresh": "Refresh",
    "logs.clear": "Clear Logs"
  },
  "fr": {
    "app.title": "EasySave",
    "menu.file": "Fichier",
    "menu.file.download": "Télécharger la sauvegarde",
    "menu.file.save": "Enregistrer le projet",
    "menu.file.exit": "Quitter",
    "menu.settings": "Paramètres",
    "menu.settings.autosave": "Activer/Désactiver l'auto-sauvegarde",
    "menu.settings.config": "Modifier la configuration",
    "menu.view": "Affichage",
    "menu.view.logs": "Afficher les logs",
    "backup.title": "Opérations de sauvegarde",
    "backup.name": "Nom",
    "backup.source": "Source",
    "backup.destination": "Destination",
    "backup.type": "Type",
    "backup.status": "Statut",
    "backup.progress": "Progression",
    "config.title": "Configuration",
    "config.language": "Langue",
    "config.logpath": "Chemin du fichier de log",
    "config.statuspath": "Chemin du fichier de statut",
    "config.autosave": "Auto-sauvegarde",
    "config.save": "Enregistrer",
    "config.cancel": "Annuler",
    "logs.title": "Logs de l'application",
    "logs.timestamp": "Horodatage",
    "logs.level": "Niveau",
    "logs.message": "Message",
    "logs.refresh": "Actualiser",
    "logs.clear": "Effacer les logs"
  }
} 